awesomedict/__init__.py
awesomedict/awesomedict.py
awesomedict-0.1.1.dist-info/LICENSE
awesomedict-0.1.1.dist-info/METADATA
awesomedict-0.1.1.dist-info/WHEEL
awesomedict-0.1.1.dist-info/top_level.txt
awesomedict-0.1.1.dist-info/RECORD
