Metadata-Version: 2.1
Name: awesomedict
Version: 0.1.1
Summary: No more KeyError! Set default values and filter via regex
Home-page: https://github.com/aayla-secura/awesomedict
Author: AaylaSecura1138
Author-email: aayla.secura.1138@gmail.com
License: UNKNOWN
Platform: UNKNOWN
Classifier: Programming Language :: Python :: 2
Classifier: Programming Language :: Python :: 2.7
Classifier: Programming Language :: Python :: 3
Classifier: Programming Language :: Python :: 3.6
Classifier: Programming Language :: Python :: 3.7
Classifier: Programming Language :: Python :: 3.8
Classifier: License :: OSI Approved :: MIT License
Classifier: Operating System :: OS Independent
